{
	"vendor": 
	[
		{
			"imgurl": "img/vdr1.jpg",
			
			"title": "s.k plumbers & sanitary co...",
			"address":"9-8-466, Chota bazar, Golconda,Hyd- 500008 (Map)"
		},
		{
			"imgurl": "img/vdr2.jpg",
			
			"title": "Novella Plumbing Pvt.Ltd....",
			"address":"flat no:108 1st floor, sun city, qayeem appartment, Hyderabad"
		},
		{
			"imgurl": "img/vdr3.jpg",
			
			"title": "Kalpana Plumbing Services....",
			"address":"flat no:108 1st floor, sun city, qayeem appartment, Hyderabad"
		},
		{
			"imgurl": "img/vdr4.jpg",
			
			"title": "AAA Plumbing Enge....",
			"address":"flat no:108 1st floor, sun city, qayeem appartment, Hyderabad"
		},
		{
			"imgurl": "img/vdr5.jpg",
			
			"title": "Taj Plumbing contractor...",
			"address":"flat no:108 1st floor, sun city, qayeem appartment, Hyderabad"
		},
		{
			"imgurl": "img/vdr6.jpg",
			
			"title": "s.k plumbers & sanitary co...",
			"address":"9-8-466, Chota bazar, Golconda,Hyd- 500008 (Map)"
		},
		{
			"imgurl": "img/vdr7.jpg",
			
			"title": "Novella Plumbing Pvt.Ltd....",
			"address":"flat no:108 1st floor, sun city, qayeem appartment, Hyderabad"
		},
		{
			"imgurl": "img/vdr8.jpg",
			
			"title": "Kalpana Plumbing Services....",
			"address":"flat no:108 1st floor, sun city, qayeem appartment, Hyderabad"
		},
		{
			"imgurl": "img/vdr9.jpg",
			
			"title": "AAA Plumbing Enge....",
			"address":"flat no:108 1st floor, sun city, qayeem appartment, Hyderabad"
		},
		{
			"imgurl": "img/vdr10.jpg",
			
			"title": "Taj Plumbing contractor...",
			"address":"flat no:108 1st floor, sun city, qayeem appartment, Hyderabad"
		}
		]
		}
		